PySPG-5.0.3.data/scripts/spg-csv.py
PySPG-5.0.3.data/scripts/spg-db.py
PySPG-5.0.3.data/scripts/spg-plotter.py
PySPG-5.0.3.data/scripts/spg-run-standalone.py
PySPG-5.0.3.data/scripts/spg-run-threaded.py
PySPG-5.0.3.data/scripts/spg-table.py
spg/__init__.py
spg/base/__init__.py
spg/base/iterator.py
spg/base/parser.py
spg/cmdline/__init__.py
spg/cmdline/base.py
spg/master/__init__.py
spg/master/base.py
spg/plot/__init__.py
spg/plot/base.py
spg/plot/mpl_base.py
spg/plot/mpl_spg.py
spg/plot/notebook.py
spg/runner/__init__.py
spg/runner/exchange.py
spg/runner/queue.py
spg/runner/single.py
spg/runner/threaded.py
spg/simulation/__init__.py
spg/simulation/atom.py
spg/simulation/ensemble.py
spg/simulation/paramdb.py
spg/simulation/simple.py
spg/utils/__init__.py
spg/utils/check_params.py
spg/utils/load_configs.py
spg/utils/tools.py
PySPG-5.0.3.dist-info/LICENCE
PySPG-5.0.3.dist-info/METADATA
PySPG-5.0.3.dist-info/WHEEL
PySPG-5.0.3.dist-info/top_level.txt
PySPG-5.0.3.dist-info/RECORD
