Metadata-Version: 2.1
Name: PySPG
Version: 5.0.3
Summary: Python Systematic Parameter Generator
Home-page: https://github.com/tessonec/PySPG
Author: Claudio J. Tessone
Author-email: claudio.tessone@uzh.ch
Keywords: simulations parameters optimisation
Classifier: Development Status :: 5 - Production/Stable
Classifier: Intended Audience :: Science/Research
Classifier: Intended Audience :: End Users/Desktop
Classifier: Intended Audience :: Developers
Classifier: Environment :: Console
Classifier: License :: OSI Approved :: GNU General Public License v3 (GPLv3)
Classifier: Natural Language :: English
Classifier: Operating System :: OS Independent
Classifier: Programming Language :: Python :: 3
Classifier: Topic :: Scientific/Engineering :: Information Analysis
Classifier: Topic :: Scientific/Engineering
Classifier: Topic :: Software Development :: Libraries :: Python Modules
License-File: LICENCE
Requires-Dist: tqdm
Requires-Dist: pandas (>=1.1)
Requires-Dist: numpy (>=1.10)
Requires-Dist: matplotlib
